multilayerpy/__init__.py
multilayerpy/build.py
multilayerpy/optimize.py
multilayerpy/simulate.py
multilayerpy-1.0.1.dist-info/LICENSE
multilayerpy-1.0.1.dist-info/METADATA
multilayerpy-1.0.1.dist-info/WHEEL
multilayerpy-1.0.1.dist-info/top_level.txt
multilayerpy-1.0.1.dist-info/RECORD
