Metadata-Version: 2.1
Name: multilayerpy
Version: 1.0.1
Summary: Build, run and optimise kinetic multi-layer models of aerosols and films
Home-page: https://github.com/tintin554/multilayerpy
Author: Adam Milsom
Author-email: a.milsom.2@bham.ac.uk
License: GPL3.0
Platform: UNKNOWN
Classifier: License :: OSI Approved :: GNU General Public License v3 or later (GPLv3+)
Classifier: Programming Language :: Python :: 3
Classifier: Programming Language :: Python :: 3.7
Requires-Dist: scipy (>=1.7.1)
Requires-Dist: numpy
Requires-Dist: matplotlib
Requires-Dist: emcee
